rocketmq/__init__.py
rocketmq/client.py
rocketmq/consts.py
rocketmq/exceptions.py
rocketmq/ffi.py
rocketmq_client_python-0.5.0rc5.dist-info/METADATA
rocketmq_client_python-0.5.0rc5.dist-info/RECORD
rocketmq_client_python-0.5.0rc5.dist-info/WHEEL
rocketmq_client_python-0.5.0rc5.dist-info/top_level.txt
samples/__init__.py
samples/consumer.py
samples/producer.py
